dialog/__init__.py
dialog/bases.py
dialog/utils.py
dialog/shared/__init__.py
dialog/shared/storage.py
dialog/shared/types.py
dialog/shared/utils.py
dialog/telegram/__init__.py
dialog/telegram/dialog.py
dialog/telegram/types.py
dialog/vk/__init__.py
dialog/vk/dialog.py
dialog/vk/middlewares.py
dialog/vk/types.py
dialog/vk/utils.py
easy_dialogs-0.3.8b0.dist-info/METADATA
easy_dialogs-0.3.8b0.dist-info/WHEEL
easy_dialogs-0.3.8b0.dist-info/top_level.txt
easy_dialogs-0.3.8b0.dist-info/RECORD
