Metadata-Version: 2.1
Name: easy-dialogs
Version: 0.3.8b0
Summary: A mini-framework for creating chatbots.Facilitates the creation of relationships and transitions between scenes (states).
Home-page: https://github.com/MaximZayats/aiogram-dialog
Author: Maxim
Author-email: maximzayats1@gmail.com
License: UNKNOWN
Keywords: python,fsm,telegram,asyncio,chatbot,bot-framework,vk,framework
Platform: UNKNOWN
Requires-Dist: aiogram (~=2.14.3)
Requires-Dist: vkbottle (~=3.0.2)
